aldryn_forms/__init__.py
aldryn_forms/action_backends.py
aldryn_forms/action_backends_base.py
aldryn_forms/apps.py
aldryn_forms/cms_apps.py
aldryn_forms/cms_plugins.py
aldryn_forms/compat.py
aldryn_forms/constants.py
aldryn_forms/fields.py
aldryn_forms/forms.py
aldryn_forms/helpers.py
aldryn_forms/models.py
aldryn_forms/settings_migrations.py
aldryn_forms/signals.py
aldryn_forms/urls.py
aldryn_forms/utils.py
aldryn_forms/validators.py
aldryn_forms/views.py
aldryn_forms/widgets.py
aldryn_forms/admin/__init__.py
aldryn_forms/admin/base.py
aldryn_forms/admin/exporter.py
aldryn_forms/admin/forms.py
aldryn_forms/admin/utils.py
aldryn_forms/admin/views.py
aldryn_forms/api/__init__.py
aldryn_forms/api/pagination.py
aldryn_forms/api/permissions.py
aldryn_forms/api/serializers.py
aldryn_forms/api/utils.py
aldryn_forms/api/views.py
aldryn_forms/api/webhook.py
aldryn_forms/contrib/__init__.py
aldryn_forms/contrib/email_notifications/__init__.py
aldryn_forms/contrib/email_notifications/apps.py
aldryn_forms/contrib/email_notifications/cms_plugins.py
aldryn_forms/contrib/email_notifications/helpers.py
aldryn_forms/contrib/email_notifications/models.py
aldryn_forms/contrib/email_notifications/notification.py
aldryn_forms/contrib/email_notifications/migrations/0001_initial.py
aldryn_forms/contrib/email_notifications/migrations/0002_form_plugin_add_missing_permission.py
aldryn_forms/contrib/email_notifications/migrations/0003_auto_20180206_1733.py
aldryn_forms/contrib/email_notifications/migrations/0004_auto_20190104_1242.py
aldryn_forms/contrib/email_notifications/migrations/0005_add_field_reply_to_email.py
aldryn_forms/contrib/email_notifications/migrations/0006_alter_emailnotification_id.py
aldryn_forms/contrib/email_notifications/migrations/__init__.py
aldryn_forms/contrib/email_notifications/static/email_notifications/admin/email-notifications.css
aldryn_forms/locale/cs/LC_MESSAGES/django.mo
aldryn_forms/locale/cs/LC_MESSAGES/django.po
djangocms_aldryn_forms-8.5.0.dist-info/licenses/LICENSE.txt
djangocms_aldryn_forms-8.5.0.dist-info/METADATA
djangocms_aldryn_forms-8.5.0.dist-info/WHEEL
djangocms_aldryn_forms-8.5.0.dist-info/top_level.txt
djangocms_aldryn_forms-8.5.0.dist-info/RECORD
