Metadata-Version: 2.4
Name: djangocms-aldryn-forms
Version: 8.5.0
Summary: Create forms and embed them on CMS pages.
Home-page: https://github.com/CZ-NIC/djangocms-aldryn-forms
Author: Divio AG
Author-email: info@divio.ch
License: BSD
Classifier: Development Status :: 5 - Production/Stable
Classifier: Environment :: Web Environment
Classifier: Intended Audience :: Developers
Classifier: License :: OSI Approved :: BSD License
Classifier: Operating System :: OS Independent
Classifier: Programming Language :: Python
Classifier: Programming Language :: Python :: 3
Classifier: Programming Language :: Python :: 3.10
Classifier: Programming Language :: Python :: 3.11
Classifier: Programming Language :: Python :: 3.12
Classifier: Framework :: Django CMS :: 4.1
Classifier: Framework :: Django CMS :: 5.0
Classifier: Topic :: Internet :: WWW/HTTP
Classifier: Topic :: Internet :: WWW/HTTP :: Dynamic Content
Classifier: Topic :: Software Development
Classifier: Topic :: Software Development :: Libraries
Requires-Python: >=3.10
License-File: LICENSE.txt
Requires-Dist: django-cms<6,>=4.1
Requires-Dist: django-emailit~=0.2
Requires-Dist: django-filer~=3.3
Requires-Dist: django-filter~=25.1
Requires-Dist: django-formtools~=2.5
Requires-Dist: django-import-export~=4.3
Requires-Dist: django-tablib~=3.2
Requires-Dist: djangocms-alias<4,>=2.0
Requires-Dist: djangocms-attributes-field~=4.1
Requires-Dist: djangocms-text~=0.8
Requires-Dist: djangocms-link~=5.0
Requires-Dist: Markdown~=3.8
Requires-Dist: easy-thumbnails[svg]~=2.10
Requires-Dist: requests~=2.32
Requires-Dist: djangorestframework~=3.16
Requires-Dist: jq~=1.10
Requires-Dist: jsonschema~=4.25
Provides-Extra: captcha
Requires-Dist: django-simple-captcha~=0.6; extra == "captcha"
Dynamic: license-file
